tatoo_cli-0.4.0.dist-info/zip-safe
tatoo_cli-0.4.0.dist-info/RECORD
tatoo_cli-0.4.0.dist-info/DESCRIPTION.rst
tatoo_cli-0.4.0.dist-info/METADATA
tatoo_cli-0.4.0.dist-info/entry_points.txt
tatoo_cli-0.4.0.dist-info/top_level.txt
tatoo_cli-0.4.0.dist-info/metadata.json
tatoo_cli-0.4.0.dist-info/WHEEL
tatoo_cli/_click_customization.py
tatoo_cli/_version.py
tatoo_cli/commands.py
tatoo_cli/signals.py
tatoo_cli/interfaces.py
tatoo_cli/__init__.py
tatoo_cli/extension.py
tatoo_cli/tasks.py
