Metadata-Version: 2.0
Name: tatoo-cli
Version: 0.4.0
Summary: Command-line interface for tatoo library
Home-page: https://github.com/malinoff/tatoo-cli
Author: Dmitry Malinovsky
Author-email: damalinov@gmail.com
License: BSD-3
Keywords: tatoo cli command line interface
Platform: linux
Platform: osx
Platform: windows
Classifier: Development Status :: 4 - Beta
Classifier: Intended Audience :: Developers
Classifier: Natural Language :: English
Classifier: Programming Language :: Python :: 2
Classifier: Programming Language :: Python :: 2.6
Classifier: Programming Language :: Python :: 2.7
Classifier: Programming Language :: Python :: 3
Classifier: Programming Language :: Python :: 3.3
Classifier: Programming Language :: Python :: 3.4
Classifier: Programming Language :: Python :: Implementation :: CPython
Classifier: Programming Language :: Python :: Implementation :: PyPy
Requires-Dist: tatoo (>=0.7)
Requires-Dist: click (>=3.3)
Requires-Dist: funcsigs (>=0.4); python_version=='2.6' or python_version=='2.7'
